gdatalog/__init__.py
gdatalog/__main__.py
gdatalog/cli.py
gdatalog/delta_terms.py
gdatalog/program.py
gdatalog/server.py
gdatalog/utils.py
gdatalog-0.3.6.dist-info/LICENSE
gdatalog-0.3.6.dist-info/METADATA
gdatalog-0.3.6.dist-info/WHEEL
gdatalog-0.3.6.dist-info/RECORD
